linux_command_logger/__init__.py
linux_command_logger/auto_commit.py
linux_command_logger/explain.py
linux_command_logger/extract.py
linux_command_logger-0.1.0.dist-info/METADATA
linux_command_logger-0.1.0.dist-info/WHEEL
linux_command_logger-0.1.0.dist-info/entry_points.txt
linux_command_logger-0.1.0.dist-info/top_level.txt
linux_command_logger-0.1.0.dist-info/RECORD
