Metadata-Version: 2.1
Name: linux-command-logger
Version: 0.1.0
Summary: A package to log Linux/Windows command history and generate documentation using Gemini AI.
Home-page: https://github.com/SaviPandey/log2doc
Author: Savinay Pandey
Author-email: Your Name <your@email.com>
License: MIT
Classifier: Programming Language :: Python :: 3
Classifier: License :: OSI Approved :: MIT License
Classifier: Operating System :: OS Independent
Requires-Python: >=3.6
Requires-Dist: google-generativeai
